rank_bm25.py
rank_bm25-0.2.2.dist-info/LICENSE
rank_bm25-0.2.2.dist-info/METADATA
rank_bm25-0.2.2.dist-info/WHEEL
rank_bm25-0.2.2.dist-info/top_level.txt
rank_bm25-0.2.2.dist-info/RECORD
