Metadata-Version: 2.1
Name: rank_bm25
Version: 0.2.2
Summary: Various BM25 algorithms for document ranking
Home-page: https://github.com/dorianbrown/rank_bm25
Author: D. Brown
Author-email: dorianstuartbrown@gmail.com
License: Apache2.0
Platform: UNKNOWN
Provides-Extra: dev
License-File: LICENSE
